{"404.md":"393d740d","animation-controllers_afk-animation-controller.md":"9ce23bbb","animation-controllers_animation-controllers-intro.md":"60d37f6d","animation-controllers_death-commands.md":"41fdc1ef","animation-controllers_entity-commands.md":"75613728","animation-controllers_index.md":"1440bd74","animation-controllers_respawn-commands.md":"3705e271","blocks_applying-effects.md":"ddc0f56b","blocks_block-materials.md":"bbf70d66","blocks_block-shapes.md":"027b346c","blocks_block-sounds.md":"9028023c","blocks_block-tags.md":"c1709c66","blocks_block-texture-variation.md":"bc05d03c","blocks_blocks-16.md":"b16b79f1","blocks_blocks-intro.md":"d38fd732","blocks_custom-glass-blocks.md":"5b2f2ed4","blocks_fake-blocks.md":"db582552","blocks_flipbook-textures.md":"da5d116b","blocks_index.md":"db92c273","blocks_legacy-block-tags.md":"843fff5f","blocks_ore-loot-tables.md":"1005e469","blocks_parts-of-custom-tree.md":"e0537ec9","blocks_rotatable-blocks.md":"433c5590","blocks_troubleshooting-blocks.md":"9ae2a61c","commands_index.md":"e2d74a8b","commands_loading-commands.md":"7dfc150e","commands_mcfunction.md":"734a7fe3","commands_nbt-commands.md":"ff7b4e62","commands_relative-coordinates.md":"9ad55c20","commands_scoreboard-operations.md":"04cde84b","commands_selectors.md":"792de666","commands_tellraw.md":"12a37299","concepts_contents.md":"100f2b1e","concepts_emojis.md":"81bb9da9","concepts_index.md":"2b79bcc9","concepts_molang.md":"89ebaf4f","concepts_namespaces.md":"caf444bd","concepts_overwriting-assets.md":"010b500b","concepts_shaders.md":"99a5ba6a","concepts_sounds.md":"b3331743","concepts_subpacks.md":"b847ff44","concepts_text-and-translations.md":"615f6d03","concepts_texture-list.md":"3170e8fb","contribute-how-to.md":"7d3af0c5","contribute-style.md":"4d004a10","contribute.md":"a4b2d29d","discord.md":"7bc186bd","documentation_creative-categories.md":"9b164e44","documentation_fog-ids.md":"d6404d33","documentation_index.md":"a205cfb3","documentation_materials.md":"b5b377be","documentation_pack-structure.md":"38e534f5","documentation_projectiles.md":"f92e9e86","documentation_queries.md":"3f28923f","documentation_shared-constructs.md":"d1b162fe","documentation_sound-definitions.md":"b46ac164","entities_boat-entities.md":"4f27ced2","entities_detecting-other-entities.md":"9319c42d","entities_disabling-team-damage.md":"2176ab60","entities_dummy-components.md":"e3292568","entities_dummy-entities.md":"95a1e83c","entities_entities-intro.md":"61d36ee2","entities_entity-attack.md":"4721da6a","entities_entity-events.md":"e5e85855","entities_entity-holds-item.md":"e07a2c55","entities_entity-movement.md":"7ff17bfd","entities_entity-properties.md":"a0c19366","entities_flying-entities.md":"b9d31300","entities_index.md":"de6205ec","entities_introduction-to-aec.md":"9c8486c6","entities_invulnerable-entities.md":"585c3e6c","entities_npc-dialogs.md":"284e20c7","entities_runtime-identifier.md":"f21aaa12","entities_sleeping-entities.md":"2969ed14","entities_solid-entities.md":"1d9c3502","entities_spawn_rules.md":"eca0a609","entities_spawning-tamed-entities.md":"78f5c0bc","entities_timers.md":"8da0ddb6","entities_troubleshooting-entities.md":"77a75971","entities_vanilla-usage-components.md":"134b5380","entities_vanilla-usage-spawn-rules.md":"25a6b718","entities_village-mechanic.md":"8beaa5ff","graph-test.md":"4abd6087","guide_addons.md":"80249021","guide_advancedmanifest.md":"75526e45","guide_blockbench.md":"73ac4a70","guide_custom-entity.md":"a11fa9a8","guide_custom-item.md":"7c886677","guide_download-packs.md":"09cd2d60","guide_format-version.md":"3f1699f0","guide_index.md":"49a7c705","guide_introduction.md":"057a8e1b","guide_loot-table.md":"2e7e4296","guide_project-setup.md":"e624e77d","guide_software-preparation.md":"88e706dc","guide_troubleshooting.md":"2b5d0f1f","guide_understanding-json.md":"f9df2aff","index.md":"3c6ee37b","items_3d-items.md":"22badf48","items_custom-armor.md":"50a758c7","items_custom-weapon.md":"0e388962","items_enchantments.md":"86210ac5","items_equipped-item-commands.md":"7a8a14fa","items_index.md":"e2cc65e0","items_item-identifiers.md":"aede486b","items_items-16.md":"d7b401f7","items_items-intro.md":"6644e1e9","items_spawning-items.md":"dc0f713a","items_tool-durability.md":"9c337176","items_troubleshooting-items.md":"65db1249","items_vanilla-usage-items.md":"5df963a5","json-ui_index.md":"905575a1","json-ui_json-ui-documentation.md":"f8ff6c13","json-ui_json-ui-intro.md":"24811ee5","loot_index.md":"3bfee059","loot_item-functions.md":"5ccfe6c6","loot_loot-tables.md":"b5c88312","loot_randomized-structure-loot.md":"b8ebccd1","loot_recipes.md":"7e086a75","loot_trade-tables.md":"1c053364","loot_trading-behavior.md":"70e25ca1","meta_addon-performance.md":"547fff61","meta_addon-programming.md":"a4796025","meta_index.md":"23f75b24","meta_jq.md":"5356396c","meta_style-guide.md":"a26ef6d1","meta_useful-links.md":"dace483b","meta_using-schemas.md":"9911d806","meta_version-control.md":"be68b579","nbt_index.md":"17312397","nbt_mcstructure.md":"d2f81b04","nbt_structure-limits.md":"2cfda45c","particles_disabling-particles.md":"0f0b6e0f","particles_index.md":"efd2da06","particles_particles-and-sounds.md":"91ab09e2","particles_particles.md":"372d0af0","particles_vanilla-particles.md":"828e40b1","privacy.md":"e3f05d07","scripting_custom-command.md":"def0e474","scripting_game-tests.md":"8ee8a2f9","scripting_gametest-qna.md":"d126a2cb","scripting_index.md":"1efb6bcc","scripting_saving-loading.md":"d1378e78","scripting_scripting-intro.md":"04a0b3bd","scripting_typescript.md":"7275160e","servers_index.md":"6e5b8403","servers_server-software.md":"182ca9ea","test.md":"17ae6d77","visuals_animated-entity-texture.md":"b51de56a","visuals_animation-effects.md":"4621f065","visuals_bedrock-modeling.md":"6a562c8a","visuals_custom-skin-packs.md":"2d1863f2","visuals_death-animations.md":"1784eb87","visuals_glowing-texture.md":"a57cdc28","visuals_index.md":"bf20ced9","visuals_introduction.md":"db5090ac","visuals_leash-position.md":"295a084d","visuals_materials.md":"b0ef67d8","visuals_math-based-animations.md":"01485208","visuals_player-geometry.md":"555c113b","visuals_remove-shadows.md":"60d79091","visuals_render-controllers.md":"15a8d381","visuals_retexturing-spawn-eggs.md":"b46fe29b","world-generation_biome-tags.md":"d472d529","world-generation_biomes.md":"729f88b7","world-generation_custom-ores.md":"da7683ad","world-generation_feature-block-conditions.md":"09c848af","world-generation_feature-types.md":"311c0f9f","world-generation_heightmap-noise.md":"cf80f35a","world-generation_index.md":"f9916df6","world-generation_structure-features.md":"0998f3cb","world-generation_surface-builder.md":"0aad72a9","world-generation_world-generation-intro.md":"361a4ad8"}
